tadanounigram/__init__.py
tadanounigram/lib/count_100000sentence.pickle
tadanounigram-1.0.0.dist-info/METADATA
tadanounigram-1.0.0.dist-info/RECORD
tadanounigram-1.0.0.dist-info/WHEEL
tadanounigram-1.0.0.dist-info/top_level.txt
