Metadata-Version: 2.1
Name: tadanounigram
Version: 1.0.0
Summary: simple KATAKANA 1-gram
Home-page: https://github.com/wbydo/tadanounigram
Author: wbydo
Author-email: wbydo@users.noreply.github.com
License: MIT
Platform: UNKNOWN
